agate_charts-0.1.3.dist-info/licenses/AUTHORS.rst
agate_charts-0.1.3.dist-info/licenses/COPYING
agatecharts/__init__.py
agatecharts/colors.py
agatecharts/table.py
agatecharts/tableset.py
agatecharts/utils.py
agatecharts/charts/__init__.py
agatecharts/charts/bars.py
agatecharts/charts/base.py
agatecharts/charts/columns.py
agatecharts/charts/lines.py
agatecharts/charts/scatter.py
agate_charts-0.1.3.dist-info/METADATA
agate_charts-0.1.3.dist-info/WHEEL
agate_charts-0.1.3.dist-info/top_level.txt
agate_charts-0.1.3.dist-info/RECORD
